openalias/__init__.py
openalias/__main__.py
openalias/helpers.py
openalias/openalias.py
openalias/settings.py
openalias/version.py
openalias-1.0.2.data/scripts/openaliaspy
openalias-1.0.2.dist-info/LICENSE
openalias-1.0.2.dist-info/LICENSE.txt
openalias-1.0.2.dist-info/METADATA
openalias-1.0.2.dist-info/WHEEL
openalias-1.0.2.dist-info/top_level.txt
openalias-1.0.2.dist-info/RECORD
