Metadata-Version: 2.1
Name: openalias
Version: 1.0.2
Summary: A Python tool for easily querying OpenAlias records
Home-page: https://github.com/Privex/openalias-py
Author: Chris (Someguy123) @ Privex
Author-email: chris@privex.io
License: MIT
Platform: UNKNOWN
Classifier: Programming Language :: Python :: 3
Classifier: Programming Language :: Python :: 3.7
Classifier: Programming Language :: Python :: 3.8
Classifier: Programming Language :: Python :: 3.9
Classifier: Programming Language :: Python :: 3.10
Classifier: License :: OSI Approved :: MIT License
Classifier: Operating System :: POSIX :: Linux
Requires-Dist: privex-helpers (>=3.0.0)
Requires-Dist: dnspython (>=2.0.0)
Requires-Dist: rich (>=12)
Requires-Dist: requests
Requires-Dist: httpx
